{
  "$schema": "https://turbo.build/schema.json",
  "tasks": {
    "dev": {
      "cache": false,
      "persistent": true
    },
    "dev:ce": {
      "cache": false,
      "persistent": true
    },
    "dev:ee": {
      "cache": false,
      "persistent": true
    },
    "dev:demo": {
      "cache": false,
      "persistent": true
    },
    "build": {
      "outputs": [
        "dist/**",
        "es/**",
        "lib/**"
      ]
    },
    "build:ee": {
      "outputs": [
        "dist/**",
        "es/**",
        "lib/**"
      ]
    },
    "build:demo": {
      "outputs": [
        "dist/**",
        "es/**",
        "lib/**"
      ]
    },
    "ts-check": {
      "dependsOn": [
        "@actiontech/dms-kit#build"
      ],
      "outputs": []
    },
    "eslint": {
      "dependsOn": [
        "@actiontech/dms-kit#build"
      ],
      "outputs": []
    },
    "stylelint": {
      "dependsOn": [
        "@actiontech/dms-kit#build"
      ],
      "outputs": []
    },
    "prettier:c": {
      "dependsOn": [
        "@actiontech/dms-kit#build"
      ],
      "outputs": []
    },
    "checker": {
      "outputs": []
    },
    "base#build": {
      "dependsOn": [
        "@actiontech/dms-kit#build"
      ]
    },
    "base#build:ee": {
      "dependsOn": [
        "@actiontech/dms-kit#build"
      ]
    },
    "base#build:demo": {
      "dependsOn": [
        "@actiontech/dms-kit#build"
      ]
    }
  }
}